neurobase/__init__.py
neurobase/metrics.py
neurobase/models.py
neurobase/optimizers.py
neurobase-0.1.1.dist-info/METADATA
neurobase-0.1.1.dist-info/WHEEL
neurobase-0.1.1.dist-info/licenses/LICENSE
neurobase-0.1.1.dist-info/RECORD
