Metadata-Version: 2.4
Name: neurobase
Version: 0.1.1
Summary: NeuroBase: a small educational machine learning library with classic models and metrics.
Author-email: Shubham Mhase <shubhammhase507@gmail.com>
License: MIT License
License-File: LICENSE
Keywords: classification,education,machine-learning,regression
Classifier: Intended Audience :: Education
Classifier: License :: OSI Approved :: MIT License
Classifier: Operating System :: OS Independent
Classifier: Programming Language :: Python :: 3
Classifier: Topic :: Scientific/Engineering :: Artificial Intelligence
Requires-Python: >=3.9
Requires-Dist: numpy>=1.21
